jellyfin_api_client/__init__.py
jellyfin_api_client/api/__init__.py
jellyfin_api_client/api/activity_log/__init__.py
jellyfin_api_client/api/activity_log/get_log_entries.py
jellyfin_api_client/api/api_key/__init__.py
jellyfin_api_client/api/api_key/create_key.py
jellyfin_api_client/api/api_key/get_keys.py
jellyfin_api_client/api/api_key/revoke_key.py
jellyfin_api_client/api/artists/__init__.py
jellyfin_api_client/api/artists/get_album_artists.py
jellyfin_api_client/api/artists/get_artist_by_name.py
jellyfin_api_client/api/artists/get_artists.py
jellyfin_api_client/api/audio/__init__.py
jellyfin_api_client/api/audio/get_audio_stream.py
jellyfin_api_client/api/audio/get_audio_stream_by_container.py
jellyfin_api_client/api/audio/head_audio_stream.py
jellyfin_api_client/api/audio/head_audio_stream_by_container.py
jellyfin_api_client/api/branding/__init__.py
jellyfin_api_client/api/branding/get_branding_css.py
jellyfin_api_client/api/branding/get_branding_css_2.py
jellyfin_api_client/api/branding/get_branding_options.py
jellyfin_api_client/api/channels/__init__.py
jellyfin_api_client/api/channels/get_all_channel_features.py
jellyfin_api_client/api/channels/get_channel_features.py
jellyfin_api_client/api/channels/get_channel_items.py
jellyfin_api_client/api/channels/get_channels.py
jellyfin_api_client/api/channels/get_latest_channel_items.py
jellyfin_api_client/api/client_log/__init__.py
jellyfin_api_client/api/collection/__init__.py
jellyfin_api_client/api/collection/add_to_collection.py
jellyfin_api_client/api/collection/create_collection.py
jellyfin_api_client/api/collection/remove_from_collection.py
jellyfin_api_client/api/configuration/__init__.py
jellyfin_api_client/api/configuration/get_configuration.py
jellyfin_api_client/api/configuration/get_default_metadata_options.py
jellyfin_api_client/api/configuration/get_named_configuration.py
jellyfin_api_client/api/configuration/update_configuration.py
jellyfin_api_client/api/configuration/update_named_configuration.py
jellyfin_api_client-11.0.0.dist-info/LICENSE
jellyfin_api_client-11.0.0.dist-info/METADATA
jellyfin_api_client-11.0.0.dist-info/WHEEL
jellyfin_api_client-11.0.0.dist-info/RECORD
