Metadata-Version: 2.3
Name: jellyfin-api-client
Version: 11.0.0
Summary: A client library for accessing Jellyfin API
License: MIT
Keywords: jellyfin,api,openapi
Author: Geoffrey Coulaud
Author-email: geoffrey.coulaud@gmail.com
Requires-Python: >=3.8,<4.0
Classifier: License :: OSI Approved :: MIT License
Classifier: Programming Language :: Python :: 3
Classifier: Programming Language :: Python :: 3.8
Classifier: Programming Language :: Python :: 3.9
Classifier: Programming Language :: Python :: 3.10
Classifier: Programming Language :: Python :: 3.11
Classifier: Programming Language :: Python :: 3.12
Classifier: Programming Language :: Python :: 3.13
Requires-Dist: attrs (>=21.3.0)
Requires-Dist: httpx (>=0.20.0,<0.25.0)
Requires-Dist: python-dateutil (>=2.8.0,<3.0.0)
Project-URL: Repository, https://github.com/GeoffreyCoulaud/jellyfin-api-client
